{
    "os": "Linux-3.10.0-957.10.1.el7.x86_64-x86_64-with-glibc2.17",
    "python": "3.11.4",
    "heartbeatAt": "2023-06-21T00:01:48.905330",
    "startedAt": "2023-06-21T00:01:18.497826",
    "docker": null,
    "cuda": null,
    "args": [],
    "state": "running",
    "program": "<python with no main file>",
    "git": {
        "remote": "https://github.com/gladisor/Waves.jl.git",
        "commit": "6cd73ea0ce678495378ad1d68a6ebde886f386cb"
    },
    "email": "123.tristan.shah@gmail.com",
    "root": "/home/012761749/Waves.jl",
    "host": "coe-hpc1.sjsuad.sjsu.edu",
    "username": "012761749",
    "executable": "/home/012761749/Waves.jl/.CondaPkg/env/bin/python",
    "cpu_count": 28,
    "cpu_count_logical": 28,
    "cpu_freq": {
        "current": 1240.4258571428575,
        "min": 1200.0,
        "max": 3200.0
    },
    "cpu_freq_per_core": [
        {
            "current": 1291.259,
            "min": 1200.0,
            "max": 3200.0
        },
        {
            "current": 1225.585,
            "min": 1200.0,
            "max": 3200.0
        },
        {
            "current": 1374.755,
            "min": 1200.0,
            "max": 3200.0
        },
        {
            "current": 1199.951,
            "min": 1200.0,
            "max": 3200.0
        },
        {
            "current": 1356.445,
            "min": 1200.0,
            "max": 3200.0
        },
        {
            "current": 1295.41,
            "min": 1200.0,
            "max": 3200.0
        },
        {
            "current": 1200.195,
            "min": 1200.0,
            "max": 3200.0
        },
        {
            "current": 1200.195,
            "min": 1200.0,
            "max": 3200.0
        },
        {
            "current": 1381.225,
            "min": 1200.0,
            "max": 3200.0
        },
        {
            "current": 1200.073,
            "min": 1200.0,
            "max": 3200.0
        },
        {
            "current": 1199.951,
            "min": 1200.0,
            "max": 3200.0
        },
        {
            "current": 1199.951,
            "min": 1200.0,
            "max": 3200.0
        },
        {
            "current": 1399.78,
            "min": 1200.0,
            "max": 3200.0
        },
        {
            "current": 1199.951,
            "min": 1200.0,
            "max": 3200.0
        },
        {
            "current": 1218.75,
            "min": 1200.0,
            "max": 3200.0
        },
        {
            "current": 1199.951,
            "min": 1200.0,
            "max": 3200.0
        },
        {
            "current": 1393.432,
            "min": 1200.0,
            "max": 3200.0
        },
        {
            "current": 1199.951,
            "min": 1200.0,
            "max": 3200.0
        },
        {
            "current": 1300.048,
            "min": 1200.0,
            "max": 3200.0
        },
        {
            "current": 1199.951,
            "min": 1200.0,
            "max": 3200.0
        },
        {
            "current": 1200.073,
            "min": 1200.0,
            "max": 3200.0
        },
        {
            "current": 1200.195,
            "min": 1200.0,
            "max": 3200.0
        },
        {
            "current": 1200.073,
            "min": 1200.0,
            "max": 3200.0
        },
        {
            "current": 1200.073,
            "min": 1200.0,
            "max": 3200.0
        },
        {
            "current": 1200.073,
            "min": 1200.0,
            "max": 3200.0
        },
        {
            "current": 1200.073,
            "min": 1200.0,
            "max": 3200.0
        },
        {
            "current": 1267.578,
            "min": 1200.0,
            "max": 3200.0
        },
        {
            "current": 1199.951,
            "min": 1200.0,
            "max": 3200.0
        }
    ],
    "disk": {
        "total": 99.0966796875,
        "used": 75.95627975463867
    },
    "memory": {
        "total": 62.67687225341797
    }
}
